[
  {
    "category": "used",
    "name": "2021 Ford Mustang EcoBoost",
    "vin": "1FA6P8TH8M5155254",
    "stock": "P13084",
    "exterior": "",
    "interior": "",
    "engine": "Intercooled Turbo Premium Unleaded I-4 2.3 L/140",
    "transmission": "Automatic",
    "carfax": "https://www.carfax.com/VehicleHistory/p/Report.cfx?partner=TVO_0&vin=1FA6P8TH8M5155254&source=BUP",
    "image": "https://content.homenetiol.com/2000157/2065512/0x0/b71f6f7406a44365a50e114c5881ea91.jpg",
    "price": "$29,694",
    "sutherlins_price": "$26,995",
    "mileage": "44,029 Miles"
  },
  {
    "category": "used",
    "name": "2019 Audi A5 Sportback Prestige",
    "vin": "WAUFNCF54KA026773",
    "stock": "P12994",
    "exterior": "",
    "interior": "",
    "engine": "Intercooled Turbo Premium Unleaded I-4 2.0 L/121",
    "transmission": "Automatic",
    "carfax": "https://www.carfax.com/VehicleHistory/p/Report.cfx?partner=TVO_0&vin=WAUFNCF54KA026773&source=BUP",
    "image": "https://content.homenetiol.com/2000157/2065512/0x0/a4f6707b15fb4be88360eb485036c8e7.jpg",
    "price": "$29,699",
    "sutherlins_price": "$26,999",
    "mileage": "39,737 Miles"
  },
  {
    "category": "used",
    "name": "2023 GMC Acadia SLT",
    "vin": "1GKKNML48PZ147273",
    "stock": "P12873A",
    "exterior": "",
    "interior": "",
    "engine": "Turbocharged Gas I4 2.0L/",
    "transmission": "Automatic",
    "carfax": "https://www.carfax.com/VehicleHistory/p/Report.cfx?partner=TVO_0&vin=1GKKNML48PZ147273&source=BUP",
    "image": "https://content.homenetiol.com/2000157/2065512/0x0/8e56c8c8c0b547c4bb92b3554c14ef66.jpg",
    "price": "$30,349",
    "sutherlins_price": "$27,590",
    "mileage": "64,805 Miles"
  },
  {
    "category": "used",
    "name": "2022 Hyundai Santa Fe Limited",
    "vin": "5NMS44AL8NH446742",
    "stock": "P12922",
    "exterior": "",
    "interior": "",
    "engine": "Intercooled Turbo Regular Unleaded I-4 2.5 L/152",
    "transmission": "Automatic",
    "carfax": "https://www.carfax.com/VehicleHistory/p/Report.cfx?partner=TVO_0&vin=5NMS44AL8NH446742&source=BUP",
    "image": "https://content.homenetiol.com/2000157/2065512/0x0/e12d0cf7cda7401db1639a08023f336b.jpg",
    "price": "$30,434",
    "sutherlins_price": "$27,667",
    "mileage": "8,468 Miles",
    "age": 41
  },
  {
    "category": "used",
    "name": "2021 Nissan Titan SV",
    "vin": "1N6AA1ED7MN526599",
    "stock": "P12935",
    "exterior": "",
    "interior": "",
    "engine": "Premium Unleaded V-8 5.6 L/339",
    "transmission": "Automatic",
    "carfax": "https://www.carfax.com/VehicleHistory/p/Report.cfx?partner=TVO_0&vin=1N6AA1ED7MN526599&source=BUP",
    "image": "https://content.homenetiol.com/2000157/2065512/0x0/1a5ce784ffbd4ea1a37a5bb6573751e5.jpg",
    "price": "$30,787",
    "sutherlins_price": "$27,988",
    "mileage": "60,129 Miles",
    "age": 39
  },
  {
    "category": "used",
    "name": "2024 Nissan Pathfinder S",
    "vin": "5N1DR3AA7RC239391",
    "stock": "P12890",
    "exterior": "",
    "interior": "",
    "engine": "Regular Unleaded V-6 3.5 L/213",
    "transmission": "Automatic",
    "carfax": "https://www.carfax.com/VehicleHistory/p/Report.cfx?partner=TVO_0&vin=5N1DR3AA7RC239391&source=BUP",
    "image": "https://content.homenetiol.com/2000157/2065512/0x0/68be5fa5ba7a4f51b7ba744a91f098be.jpg",
    "price": "$30,787",
    "sutherlins_price": "$27,988",
    "mileage": "18,298 Miles",
    "age": 55
  },
  {
    "category": "used",
    "name": "2024 Toyota RAV4 XLE",
    "vin": "2T3W1RFV4RW334412",
    "stock": "P13072",
    "exterior": "",
    "interior": "",
    "engine": "Regular Unleaded I-4 2.5 L/152",
    "transmission": "Automatic",
    "carfax": "https://www.carfax.com/VehicleHistory/p/Report.cfx?partner=TVO_0&vin=2T3W1RFV4RW334412&source=BUP",
    "image": "https://content.homenetiol.com/2000157/2065512/0x0/stock_images/5/2024TOS11_640/2024TOS111927533_640_01.jpg",
    "price": "$30,793",
    "sutherlins_price": "$27,994",
    "mileage": "N/A"
  },
  {
    "category": "used",
    "name": "2020 RAM 1500 Lone Star",
    "vin": "1C6RREFT3LN288865",
    "stock": "KP1032",
    "exterior": "",
    "interior": "",
    "engine": "Regular Unleaded V-8 5.7 L/345",
    "transmission": "Automatic",
    "carfax": "https://www.carfax.com/VehicleHistory/p/Report.cfx?partner=TVO_0&vin=1C6RREFT3LN288865&source=BUP",
    "image": "https://content.homenetiol.com/2000157/2065512/0x0/17036466f8754a0fb67f2a772c3c17a5.jpg",
    "price": "$30,794",
    "sutherlins_price": "$27,995",
    "mileage": "70,166 Miles"
  },
  {
    "category": "used",
    "name": "2023 RAM 1500 Classic SLT",
    "vin": "1C6RR7LG5PS526791",
    "stock": "P13083",
    "exterior": "",
    "interior": "",
    "engine": "Regular Unleaded V-6 3.6 L/220",
    "transmission": "Automatic",
    "carfax": "https://www.carfax.com/VehicleHistory/p/Report.cfx?partner=TVO_0&vin=1C6RR7LG5PS526791&source=BUP",
    "image": "https://content.homenetiol.com/2000157/2065512/0x0/f41ca05d6964433c86a86a214fd884bc.jpg",
    "price": "$30,794",
    "sutherlins_price": "$27,995",
    "mileage": "48,485 Miles"
  },
  {
    "category": "used",
    "name": "2024 Nissan Pathfinder S",
    "vin": "5N1DR3AA2RC239086",
    "stock": "P12889",
    "exterior": "",
    "interior": "",
    "engine": "Regular Unleaded V-6 3.5 L/213",
    "transmission": "Automatic",
    "carfax": "https://www.carfax.com/VehicleHistory/p/Report.cfx?partner=TVO_0&vin=5N1DR3AA2RC239086&source=BUP",
    "image": "https://content.homenetiol.com/2000157/2065512/0x0/4200aac755004520af633edaaae961e9.jpg",
    "price": "$30,798",
    "sutherlins_price": "$27,998",
    "mileage": "21,251 Miles",
    "age": 55
  },
  {
    "category": "used",
    "name": "2022 INFINITI Q50 LUXE",
    "vin": "JN1EV7BP9NM311875",
    "stock": "P13077",
    "exterior": "",
    "interior": "",
    "engine": "Twin Turbo Premium Unleaded V-6 3.0 L/183",
    "transmission": "Automatic",
    "carfax": "https://www.carfax.com/VehicleHistory/p/Report.cfx?partner=TVO_0&vin=JN1EV7BP9NM311875&source=BUP",
    "image": "https://content.homenetiol.com/2000157/2065512/0x0/stock_images/5/2022INC25_640/2022INC250011_640_01.jpg",
    "price": "$31,894",
    "sutherlins_price": "$28,995",
    "mileage": "25,689 Miles"
  },
  {
    "category": "used",
    "name": "2018 GMC Yukon SLE",
    "vin": "1GKS2AKC1JR230437",
    "stock": "P13087",
    "exterior": "",
    "interior": "",
    "engine": "Gas V8 5.3L/325",
    "transmission": "Automatic",
    "carfax": "https://www.carfax.com/VehicleHistory/p/Report.cfx?partner=TVO_0&vin=1GKS2AKC1JR230437&source=BUP",
    "image": "https://content.homenetiol.com/2000157/2065512/0x0/stock_images/5/2018GMS03_640/2018GMS030037_640_01.jpg",
    "price": "$31,894",
    "sutherlins_price": "$28,995",
    "mileage": "83,980 Miles"
  },
  {
    "category": "used",
    "name": "2022 INFINITI Q50 LUXE",
    "vin": "JN1EV7BP1NM311112",
    "stock": "P13068",
    "exterior": "",
    "interior": "",
    "engine": "Twin Turbo Premium Unleaded V-6 3.0 L/183",
    "transmission": "Automatic",
    "carfax": "https://www.carfax.com/VehicleHistory/p/Report.cfx?partner=TVO_0&vin=JN1EV7BP1NM311112&source=BUP",
    "image": "https://content.homenetiol.com/2000157/2065512/0x0/0f5f54208afc4431bc9ca457eb8785af.jpg",
    "price": "$32,987",
    "sutherlins_price": "$29,988",
    "mileage": "34,666 Miles"
  },
  {
    "category": "used",
    "name": "2022 Nissan Rogue Platinum",
    "vin": "JN8BT3DC1NW118458",
    "stock": "P13093",
    "exterior": "",
    "interior": "Wheat",
    "engine": "Intercooled Turbo Regular Unleaded I-3 1.5 L/91",
    "transmission": "CVT",
    "carfax": "https://www.carfax.com/VehicleHistory/p/Report.cfx?partner=TVO_0&vin=JN8BT3DC1NW118458&source=BUP",
    "image": "https://content.homenetiol.com/2000157/2065512/0x0/stock_images/5/2022NIS11_640/2022NIS110048_640_01.jpg",
    "price": "$32,994",
    "sutherlins_price": "$29,995",
    "mileage": "10,731 Miles"
  },
  {
    "category": "used",
    "name": "2021 Dodge Challenger R/T",
    "vin": "2C3CDZBT1MH655206",
    "stock": "25331A",
    "exterior": "",
    "interior": "",
    "engine": "Regular Unleaded V-8 5.7 L/345",
    "transmission": "Automatic",
    "carfax": "https://www.carfax.com/VehicleHistory/p/Report.cfx?partner=TVO_0&vin=2C3CDZBT1MH655206&source=BUP",
    "image": "https://content.homenetiol.com/2000157/2065512/0x0/73cbc39d5a21460cbc492db79279dfc4.jpg",
    "price": "$34,087",
    "sutherlins_price": "$30,988",
    "mileage": "13,598 Miles"
  },
  {
    "category": "used",
    "name": "2023 Nissan Titan SV",
    "vin": "1N6AA1EE4PN110183",
    "stock": "P13022",
    "exterior": "",
    "interior": "",
    "engine": "Premium Unleaded V-8 5.6 L/339",
    "transmission": "Automatic",
    "carfax": "https://www.carfax.com/VehicleHistory/p/Report.cfx?partner=TVO_0&vin=1N6AA1EE4PN110183&source=BUP",
    "image": "https://content.homenetiol.com/2000157/2065512/0x0/129d3ed096ea4ffc9ac580c822bf13f7.jpg",
    "price": "$34,087",
    "sutherlins_price": "$30,988",
    "mileage": "50,556 Miles"
  },
  {
    "category": "used",
    "name": "2023 Jeep Wrangler 4xe Sahara High Altitude",
    "vin": "1C4JJXP60PW515950",
    "stock": "P13004",
    "exterior": "",
    "interior": "",
    "engine": "Intercooled Turbo Gas/Electric I-4 2.0 L/122",
    "transmission": "Automatic",
    "carfax": "https://www.carfax.com/VehicleHistory/p/Report.cfx?partner=TVO_0&vin=1C4JJXP60PW515950&source=BUP",
    "image": "https://content.homenetiol.com/2000157/2065512/0x0/1aa246f60b67489898d9a8ac84bfbf67.jpg",
    "price": "$34,087",
    "sutherlins_price": "$30,988",
    "mileage": "81,967 Miles"
  },
  {
    "category": "used",
    "name": "2018 Ford F-150 LARIAT",
    "vin": "1FTFW1EG3JKC66543",
    "stock": "P12991",
    "exterior": "",
    "interior": "",
    "engine": "Ecoboost 3.5L V6",
    "transmission": "Automatic",
    "carfax": "https://www.carfax.com/VehicleHistory/p/Report.cfx?partner=TVO_0&vin=1FTFW1EG3JKC66543&source=BUP",
    "image": "https://content.homenetiol.com/2000157/2065512/0x0/26bf42d546504e9888d2a3b808ba3459.jpg",
    "price": "$34,087",
    "sutherlins_price": "$30,988",
    "mileage": "39,849 Miles"
  },
  {
    "category": "used",
    "name": "2023 Ford F-150 XLT",
    "vin": "1FTFW1E56PKD96386",
    "stock": "P12919",
    "exterior": "",
    "interior": "",
    "engine": "Regular Unleaded V8 5.0 L",
    "transmission": "Automatic",
    "carfax": "https://www.carfax.com/VehicleHistory/p/Report.cfx?partner=TVO_0&vin=1FTFW1E56PKD96386&source=BUP",
    "image": "https://content.homenetiol.com/2000157/2065512/0x0/d2686de34e544643a8719d5c3b5cf2e2.jpg",
    "price": "$38,487",
    "sutherlins_price": "$34,988",
    "mileage": "39,140 Miles",
    "age": 41
  },
  {
    "category": "used",
    "name": "2022 Audi A6 Sedan Premium",
    "vin": "WAUK2BF20NN024944",
    "stock": "024944",
    "exterior": "",
    "interior": "",
    "engine": "Intercooled Turbo Gas/Electric V-6 3.0 L/183",
    "transmission": "Automatic",
    "carfax": "https://www.carfax.com/VehicleHistory/p/Report.cfx?partner=TVO_0&vin=WAUK2BF20NN024944&source=BUP",
    "image": "https://content.homenetiol.com/2000157/2065512/0x0/120a4d8ee9374598ba891d8fc31298f4.jpg",
    "price": "$39,587",
    "sutherlins_price": "$35,988",
    "mileage": "29,486 Miles"
  },
  {
    "category": "used",
    "name": "2022 Chevrolet Silverado 1500 LT",
    "vin": "1GCPDKEK7NZ629539",
    "stock": "P12946",
    "exterior": "",
    "interior": "",
    "engine": "Turbocharged Gas I4 2.7L/166",
    "transmission": "Automatic",
    "carfax": "https://www.carfax.com/VehicleHistory/p/Report.cfx?partner=TVO_0&vin=1GCPDKEK7NZ629539&source=BUP",
    "image": "https://content.homenetiol.com/2000157/2065512/0x0/cc838a77221e44cbb6cc0b1888631cbd.jpg",
    "price": "$39,587",
    "sutherlins_price": "$35,988",
    "mileage": "21,964 Miles"
  },
  {
    "category": "used",
    "name": "2008 Bentley Continental GT Base",
    "vin": "SCBDR33W58C055744",
    "stock": "P13046",
    "exterior": "",
    "interior": "N/A",
    "engine": "Gas W12 6.0L/366",
    "transmission": "Automatic",
    "carfax": "https://www.carfax.com/VehicleHistory/p/Report.cfx?partner=TVO_0&vin=SCBDR33W58C055744&source=BUP",
    "image": "https://content.homenetiol.com/2000157/2065512/0x0/bee18d217b0b435786edb141e7b5259a.jpg",
    "price": "$43,987",
    "sutherlins_price": "$39,988",
    "mileage": "50,481 Miles"
  },
  {
    "category": "used",
    "name": "2021 BMW X5 sDrive40i",
    "vin": "5UXCR4C02M9F40605",
    "stock": "25580A",
    "exterior": "",
    "interior": "Cognac",
    "engine": "Intercooled Turbo Gas/Electric I-6 3.0 L/183",
    "transmission": "Automatic",
    "carfax": "https://www.carfax.com/VehicleHistory/p/Report.cfx?partner=TVO_0&vin=5UXCR4C02M9F40605&source=BUP",
    "image": "https://content.homenetiol.com/2000157/2065512/0x0/stock_images/5/2021BMS19_640/2021BMS190034_640_01.jpg",
    "price": "$43,998",
    "sutherlins_price": "$39,998",
    "mileage": "30,537 Miles"
  },
  {
    "category": "used",
    "name": "2024 Nissan Pathfinder Platinum",
    "vin": "5N1DR3DJ3RC315474",
    "stock": "P13076",
    "exterior": "",
    "interior": "",
    "engine": "Regular Unleaded V-6 3.5 L/213",
    "transmission": "Automatic",
    "carfax": "https://www.carfax.com/VehicleHistory/p/Report.cfx?partner=TVO_0&vin=5N1DR3DJ3RC315474&source=BUP",
    "image": "https://content.homenetiol.com/2000157/2065512/0x0/fde1a7edc33348578653bc16591068c8.jpg",
    "price": "$50,594",
    "sutherlins_price": "$45,995",
    "mileage": "8,219 Miles"
  },
  {
    "category": "used",
    "name": "2024 Toyota Highlander XSE",
    "vin": "5TDKDRBH2RS532073",
    "stock": "P13064",
    "exterior": "",
    "interior": "",
    "engine": "Intercooled Turbo Regular Unleaded I-4 2.4 L/146",
    "transmission": "Automatic",
    "carfax": "https://www.carfax.com/VehicleHistory/p/Report.cfx?partner=TVO_0&vin=5TDKDRBH2RS532073&source=BUP",
    "image": "https://content.homenetiol.com/2000157/2065512/0x0/e0f37fadbc3442268cc8be2cef4c13e0.jpg",
    "price": "$52,787",
    "sutherlins_price": "$47,988",
    "mileage": "10,972 Miles"
  },
  {
    "category": "used",
    "name": "2024 Toyota Tundra 4WD Limited Hybrid",
    "vin": "5TFJC5DB3RX071279",
    "stock": "KP1029",
    "exterior": "",
    "interior": "",
    "engine": "Twin Turbo Gas/Electric V-6 3.4 L/210",
    "transmission": "Automatic",
    "carfax": "https://www.carfax.com/VehicleHistory/p/Report.cfx?partner=TVO_0&vin=5TFJC5DB3RX071279&source=BUP",
    "image": "https://content.homenetiol.com/2000157/2065512/0x0/f92c8d7abd3740daaaec1dbb8762285a.jpg",
    "price": "$63,683",
    "sutherlins_price": "$57,894",
    "mileage": "10,568 Miles"
  },
  {
    "category": "used",
    "name": "2023 Lexus GX 460 Luxury",
    "vin": "JTJGM7BX2P5369099",
    "stock": "25579A",
    "exterior": "",
    "interior": "Rioja Red",
    "engine": "Premium Unleaded V-8 4.6 L/281",
    "transmission": "Automatic",
    "carfax": "https://www.carfax.com/VehicleHistory/p/Report.cfx?partner=TVO_0&vin=JTJGM7BX2P5369099&source=BUP",
    "image": "https://content.homenetiol.com/2000157/2065512/0x0/2c8c7c9e5c174964a488bef2bdb78aa7.jpg",
    "price": "$71,494",
    "sutherlins_price": "$64,995",
    "mileage": "6,132 Miles"
  },
  {
    "category": "used",
    "name": "2024 RAM 1500 Laramie",
    "vin": "1C6RREJT0RN219793",
    "stock": "P12920",
    "exterior": "",
    "interior": "",
    "engine": "Gas/Electric V-8 5.7 L/345",
    "transmission": "Automatic",
    "carfax": "https://www.carfax.com/VehicleHistory/p/Report.cfx?partner=TVO_0&vin=1C6RREJT0RN219793&source=BUP",
    "image": "https://content.homenetiol.com/2000157/2065512/0x0/d230976636404dee943446f46ce386a1.jpg",
    "price": "N/A",
    "sutherlins_price": "N/A",
    "mileage": "14,323 Miles",
    "age": 41
  }
]